_examples/client/multi_transport_client_example.py
_examples/client/ping_test.py
_examples/client/simple_http_client.py
_examples/client/stdio_client_example.py
_examples/server/custom_tool_http.py
_examples/server/simple_http_server.py
_examples/server/simple_stdio.py
_examples/server/task_list_tools_http.py
mojentic_mcp/__init__.py
mojentic_mcp/client.py
mojentic_mcp/client_spec.py
mojentic_mcp/gateways.py
mojentic_mcp/mcp_http.py
mojentic_mcp/mcp_http_spec.py
mojentic_mcp/mcp_stdio.py
mojentic_mcp/mcp_stdio_spec.py
mojentic_mcp/rpc.py
mojentic_mcp/rpc_spec.py
mojentic_mcp/transports.py
mojentic_mcp/transports_spec.py
mojentic_mcp-0.7.0.dist-info/METADATA
mojentic_mcp-0.7.0.dist-info/WHEEL
mojentic_mcp-0.7.0.dist-info/top_level.txt
mojentic_mcp-0.7.0.dist-info/RECORD
