Metadata-Version: 2.4
Name: mojentic-mcp
Version: 0.7.0
Summary: Mojentic MCP is a module for the Mojentic framework that provides basic MCP server and client infrastructure for tools and chat agents.
Author-email: Stacey Vetzal <stacey@vetzal.com>
Project-URL: Homepage, https://github.com/svetzal/mojentic-mcp
Project-URL: Issues, https://github.com/svetzal/mojentic-mcp/issues
Classifier: Programming Language :: Python :: 3
Classifier: License :: OSI Approved :: MIT License
Classifier: Operating System :: OS Independent
Requires-Python: >=3.11
Requires-Dist: mojentic>=0.5.7
Requires-Dist: structlog
Requires-Dist: fastapi
Requires-Dist: uvicorn
Requires-Dist: httpx
Provides-Extra: dev
Requires-Dist: pytest>=7.0.0; extra == "dev"
Requires-Dist: pytest-spec; extra == "dev"
Requires-Dist: pytest-cov; extra == "dev"
Requires-Dist: pytest-mock>=3.10.0; extra == "dev"
Requires-Dist: flake8>=6.0.0; extra == "dev"
Requires-Dist: mkdocs; extra == "dev"
Requires-Dist: mkdocstrings[python]; extra == "dev"
Requires-Dist: griffe-fieldz; extra == "dev"
Requires-Dist: mkdocs-material; extra == "dev"
